setup.cfg
setup.py
playwork/__init__.py
playwork/command.py
playwork/routes.py
playwork/settings.py
playwork/test.py
playwork/utils.py
playwork.egg-info/PKG-INFO
playwork.egg-info/SOURCES.txt
playwork.egg-info/dependency_links.txt
playwork.egg-info/entry_points.txt
playwork.egg-info/requires.txt
playwork.egg-info/top_level.txt
playwork.egg-info/zip-safe
playwork/app/__init__.py
playwork/app/routes.py
playwork/app/views.py
playwork/app/controllers/__init__.py
playwork/app/controllers/article.py
playwork/app/controllers/user.py
playwork/app_template/__init__.py
playwork/bin/playwork-admin.py
playwork/project_template/__init__.py