Metadata-Version: 1.1
Name: playwork
Version: 0.0.1dev
Summary: tornado, web framework, framework
Home-page: https://github.com/youngershen/playwork
Author: younger shen
Author-email: younger.x.shen@gmail.com
License: MIT
Keywords: playwork,tornado,web,webframework,framework
Platform: UNKNOWN
Classifier: Development Status :: 1 - Planning
Classifier: Environment :: Web Environment
Classifier: Intended Audience :: Developers
Classifier: License :: OSI Approved :: MIT License
Classifier: Natural Language :: English
Classifier: Operating System :: POSIX
Classifier: Programming Language :: Python :: 2.7
Classifier: Topic :: Internet :: WWW/HTTP :: Dynamic Content
